bokeh_joystick_widget/__init__.py
bokeh_joystick_widget/joystick.ts
bokeh_joystick_widget/joystick_widget.ts
bokeh_joystick_widget-0.3.3.dist-info/LICENSE.md
bokeh_joystick_widget-0.3.3.dist-info/WHEEL
bokeh_joystick_widget-0.3.3.dist-info/METADATA
bokeh_joystick_widget-0.3.3.dist-info/RECORD
