Metadata-Version: 2.1
Name: bokeh-joystick-widget
Version: 0.3.3
Summary: A Bokeh on screen gesture/mouse drag based joystick widget for use in a dashboard with controls
Home-page: https://pypi.org/project/bokeh-joystick-widget/
License: MIT
Author: Danny Staple
Author-email: danny@orionrobots.co.uk
Requires-Python: >=3.9,<4.0
Classifier: License :: OSI Approved :: MIT License
Classifier: Programming Language :: Python :: 3
Classifier: Programming Language :: Python :: 3.9
Classifier: Programming Language :: Python :: 3.10
Classifier: Programming Language :: Python :: 3.11
Requires-Dist: bokeh (>=3.4.1,<4.0.0)
Project-URL: Repository, https://github.com/orionrobots/bokeh_joystick_widget
